<?xml version="1.0" encoding="UTF-8"?>

<scenario:scenario xmlns:scenario="urn:roborescue:map:scenario">
  <scenario:refuge scenario:location="49557"/>
  <scenario:refuge scenario:location="52505"/>
  <scenario:refuge scenario:location="53257"/>
  <scenario:refuge scenario:location="51691"/>
  <scenario:refuge scenario:location="49343"/>
  <scenario:fire scenario:location="49413"/>
  <scenario:fire scenario:location="49414"/>
  <scenario:fire scenario:location="49416"/>
  <scenario:fire scenario:location="49418"/>
  <scenario:fire scenario:location="49419"/>
  <scenario:fire scenario:location="49420"/>
  <scenario:fire scenario:location="49421"/>
  <scenario:fire scenario:location="49422"/>
  <scenario:fire scenario:location="49423"/>
  <scenario:fire scenario:location="49424"/>
  <scenario:fire scenario:location="49431"/>
  <scenario:fire scenario:location="49433"/>
  <scenario:fire scenario:location="49434"/>
  <scenario:fire scenario:location="49436"/>
  <scenario:fire scenario:location="49437"/>
  <scenario:fire scenario:location="49438"/>
  <scenario:fire scenario:location="49440"/>
  <scenario:fire scenario:location="49407"/>
  <scenario:hydrant scenario:location="43072"/>
  <scenario:hydrant scenario:location="50242"/>
  <scenario:hydrant scenario:location="1154"/>
  <scenario:hydrant scenario:location="51972"/>
  <scenario:hydrant scenario:location="48453"/>
  <scenario:hydrant scenario:location="5893"/>
  <scenario:hydrant scenario:location="1351"/>
  <scenario:hydrant scenario:location="53384"/>
  <scenario:hydrant scenario:location="53450"/>
  <scenario:hydrant scenario:location="48526"/>
  <scenario:hydrant scenario:location="31630"/>
  <scenario:hydrant scenario:location="13719"/>
  <scenario:hydrant scenario:location="48407"/>
  <scenario:hydrant scenario:location="41432"/>
  <scenario:hydrant scenario:location="32537"/>
  <scenario:hydrant scenario:location="34458"/>
  <scenario:hydrant scenario:location="53406"/>
  <scenario:hydrant scenario:location="50144"/>
  <scenario:hydrant scenario:location="3814"/>
  <scenario:hydrant scenario:location="49001"/>
  <scenario:hydrant scenario:location="51115"/>
  <scenario:hydrant scenario:location="42541"/>
  <scenario:hydrant scenario:location="53743"/>
  <scenario:hydrant scenario:location="6127"/>
  <scenario:hydrant scenario:location="241"/>
  <scenario:hydrant scenario:location="50482"/>
  <scenario:hydrant scenario:location="50162"/>
  <scenario:hydrant scenario:location="53619"/>
  <scenario:hydrant scenario:location="53429"/>
  <scenario:hydrant scenario:location="50230"/>
  <scenario:hydrant scenario:location="52214"/>
  <scenario:hydrant scenario:location="2230"/>
  <scenario:hydrant scenario:location="53559"/>
  <scenario:hydrant scenario:location="47671"/>
  <scenario:hydrant scenario:location="248"/>
  <scenario:hydrant scenario:location="48442"/>
  <scenario:hydrant scenario:location="51771"/>
  <scenario:hydrant scenario:location="48700"/>
  <scenario:hydrant scenario:location="51134"/>
  <scenario:hydrant scenario:location="19199"/>
  <scenario:gasstation scenario:location="50117"/>
  <scenario:civilian scenario:location="49504"/>
  <scenario:civilian scenario:location="49486"/>
  <scenario:civilian scenario:location="49511"/>
  <scenario:civilian scenario:location="49487"/>
  <scenario:civilian scenario:location="49489"/>
  <scenario:civilian scenario:location="49490"/>
  <scenario:civilian scenario:location="49531"/>
  <scenario:civilian scenario:location="49505"/>
  <scenario:civilian scenario:location="49508"/>
  <scenario:civilian scenario:location="50339"/>
  <scenario:civilian scenario:location="49511"/>
  <scenario:civilian scenario:location="49523"/>
  <scenario:civilian scenario:location="49484"/>
  <scenario:civilian scenario:location="49485"/>
  <scenario:civilian scenario:location="49525"/>
  <scenario:civilian scenario:location="49980"/>
  <scenario:civilian scenario:location="49986"/>
  <scenario:civilian scenario:location="49987"/>
  <scenario:civilian scenario:location="49981"/>
  <scenario:civilian scenario:location="49984"/>
  <scenario:civilian scenario:location="49985"/>
  <scenario:civilian scenario:location="49983"/>
  <scenario:civilian scenario:location="49984"/>
  <scenario:civilian scenario:location="49532"/>
  <scenario:civilian scenario:location="49534"/>
  <scenario:civilian scenario:location="49535"/>
  <scenario:civilian scenario:location="49978"/>
  <scenario:civilian scenario:location="50118"/>
  <scenario:civilian scenario:location="50120"/>
  <scenario:civilian scenario:location="49474"/>
  <scenario:civilian scenario:location="49477"/>
  <scenario:civilian scenario:location="49476"/>
  <scenario:civilian scenario:location="49475"/>
  <scenario:civilian scenario:location="49469"/>
  <scenario:civilian scenario:location="49471"/>
  <scenario:civilian scenario:location="49472"/>
  <scenario:civilian scenario:location="49468"/>
  <scenario:civilian scenario:location="49827"/>
  <scenario:civilian scenario:location="49829"/>
  <scenario:civilian scenario:location="49803"/>
  <scenario:civilian scenario:location="49802"/>
  <scenario:civilian scenario:location="49801"/>
  <scenario:civilian scenario:location="49553"/>
  <scenario:civilian scenario:location="49552"/>
  <scenario:civilian scenario:location="49552"/>
  <scenario:civilian scenario:location="49549"/>
  <scenario:civilian scenario:location="49548"/>
  <scenario:civilian scenario:location="49534"/>
  <scenario:civilian scenario:location="49544"/>
  <scenario:civilian scenario:location="49599"/>
  <scenario:civilian scenario:location="49693"/>
  <scenario:civilian scenario:location="49695"/>
  <scenario:civilian scenario:location="49695"/>
  <scenario:civilian scenario:location="49747"/>
  <scenario:civilian scenario:location="49746"/>
  <scenario:civilian scenario:location="7405"/>
  <scenario:civilian scenario:location="2527"/>
  <scenario:civilian scenario:location="49625"/>
  <scenario:civilian scenario:location="49574"/>
  <scenario:civilian scenario:location="49572"/>
  <scenario:civilian scenario:location="49597"/>
  <scenario:civilian scenario:location="49596"/>
  <scenario:civilian scenario:location="49595"/>
  <scenario:civilian scenario:location="49559"/>
  <scenario:civilian scenario:location="49560"/>
  <scenario:civilian scenario:location="49591"/>
  <scenario:civilian scenario:location="49575"/>
  <scenario:civilian scenario:location="49576"/>
  <scenario:civilian scenario:location="49593"/>
  <scenario:civilian scenario:location="49594"/>
  <scenario:civilian scenario:location="49592"/>
  <scenario:civilian scenario:location="49364"/>
  <scenario:civilian scenario:location="52486"/>
  <scenario:civilian scenario:location="52086"/>
  <scenario:civilian scenario:location="49363"/>
  <scenario:civilian scenario:location="51292"/>
  <scenario:civilian scenario:location="51635"/>
  <scenario:civilian scenario:location="51174"/>
  <scenario:civilian scenario:location="53116"/>
  <scenario:civilian scenario:location="52557"/>
  <scenario:civilian scenario:location="49801"/>
  <scenario:civilian scenario:location="51336"/>
  <scenario:civilian scenario:location="49826"/>
  <scenario:civilian scenario:location="51333"/>
  <scenario:civilian scenario:location="50777"/>
  <scenario:civilian scenario:location="49405"/>
  <scenario:civilian scenario:location="50031"/>
  <scenario:civilian scenario:location="49381"/>
  <scenario:civilian scenario:location="52318"/>
  <scenario:civilian scenario:location="52487"/>
  <scenario:civilian scenario:location="50565"/>
  <scenario:civilian scenario:location="52315"/>
  <scenario:civilian scenario:location="51685"/>
  <scenario:civilian scenario:location="49573"/>
  <scenario:civilian scenario:location="52583"/>
  <scenario:civilian scenario:location="51063"/>
  <scenario:civilian scenario:location="50116"/>
  <scenario:civilian scenario:location="51220"/>
  <scenario:civilian scenario:location="51181"/>
  <scenario:civilian scenario:location="49777"/>
  <scenario:civilian scenario:location="49387"/>
  <scenario:civilian scenario:location="52609"/>
  <scenario:civilian scenario:location="51736"/>
  <scenario:civilian scenario:location="49527"/>
  <scenario:civilian scenario:location="49456"/>
  <scenario:civilian scenario:location="53536"/>
  <scenario:civilian scenario:location="52148"/>
  <scenario:civilian scenario:location="49422"/>
  <scenario:civilian scenario:location="49552"/>
  <scenario:civilian scenario:location="51292"/>
  <scenario:civilian scenario:location="53046"/>
  <scenario:civilian scenario:location="51567"/>
  <scenario:civilian scenario:location="49746"/>
  <scenario:civilian scenario:location="50781"/>
  <scenario:civilian scenario:location="53230"/>
  <scenario:civilian scenario:location="52794"/>
  <scenario:civilian scenario:location="53245"/>
  <scenario:civilian scenario:location="49526"/>
  <scenario:civilian scenario:location="50120"/>
  <scenario:civilian scenario:location="50118"/>
  <scenario:civilian scenario:location="50119"/>
  <scenario:civilian scenario:location="50127"/>
  <scenario:civilian scenario:location="49979"/>
  <scenario:civilian scenario:location="49478"/>
  <scenario:civilian scenario:location="49474"/>
  <scenario:civilian scenario:location="49466"/>
  <scenario:civilian scenario:location="49465"/>
  <scenario:civilian scenario:location="49473"/>
  <scenario:civilian scenario:location="49480"/>
  <scenario:civilian scenario:location="49481"/>
  <scenario:civilian scenario:location="50052"/>
  <scenario:civilian scenario:location="49543"/>
  <scenario:civilian scenario:location="49538"/>
  <scenario:civilian scenario:location="49542"/>
  <scenario:civilian scenario:location="49540"/>
  <scenario:civilian scenario:location="49541"/>
  <scenario:civilian scenario:location="49539"/>
  <scenario:civilian scenario:location="51158"/>
  <scenario:civilian scenario:location="49862"/>
  <scenario:civilian scenario:location="49830"/>
  <scenario:civilian scenario:location="49863"/>
  <scenario:civilian scenario:location="49864"/>
  <scenario:civilian scenario:location="49976"/>
  <scenario:civilian scenario:location="49977"/>
  <scenario:civilian scenario:location="49975"/>
  <scenario:civilian scenario:location="49974"/>
  <scenario:civilian scenario:location="49951"/>
  <scenario:civilian scenario:location="49947"/>
  <scenario:civilian scenario:location="49950"/>
  <scenario:civilian scenario:location="49973"/>
  <scenario:civilian scenario:location="50018"/>
  <scenario:civilian scenario:location="49724"/>
  <scenario:civilian scenario:location="49698"/>
  <scenario:civilian scenario:location="49699"/>
  <scenario:civilian scenario:location="49700"/>
  <scenario:civilian scenario:location="49697"/>
  <scenario:civilian scenario:location="49696"/>
  <scenario:civilian scenario:location="51234"/>
  <scenario:civilian scenario:location="52608"/>
  <scenario:civilian scenario:location="52641"/>
  <scenario:civilian scenario:location="52700"/>
  <scenario:civilian scenario:location="52729"/>
  <scenario:civilian scenario:location="52951"/>
  <scenario:civilian scenario:location="52820"/>
  <scenario:civilian scenario:location="52833"/>
  <scenario:civilian scenario:location="53329"/>
  <scenario:civilian scenario:location="53235"/>
  <scenario:civilian scenario:location="52864"/>
  <scenario:civilian scenario:location="53254"/>
  <scenario:civilian scenario:location="53271"/>
  <scenario:civilian scenario:location="48457"/>
  <scenario:civilian scenario:location="53276"/>
  <scenario:civilian scenario:location="53225"/>
  <scenario:civilian scenario:location="53221"/>
  <scenario:civilian scenario:location="53279"/>
  <scenario:civilian scenario:location="49619"/>
  <scenario:civilian scenario:location="49616"/>
  <scenario:civilian scenario:location="49605"/>
  <scenario:civilian scenario:location="49569"/>
  <scenario:civilian scenario:location="49563"/>
  <scenario:civilian scenario:location="49562"/>
  <scenario:civilian scenario:location="49621"/>
  <scenario:civilian scenario:location="49622"/>
  <scenario:civilian scenario:location="49660"/>
  <scenario:civilian scenario:location="49661"/>
  <scenario:civilian scenario:location="49662"/>
  <scenario:civilian scenario:location="49663"/>
  <scenario:civilian scenario:location="49630"/>
  <scenario:civilian scenario:location="49632"/>
  <scenario:civilian scenario:location="49633"/>
  <scenario:civilian scenario:location="49689"/>
  <scenario:civilian scenario:location="49687"/>
  <scenario:civilian scenario:location="49688"/>
  <scenario:civilian scenario:location="51198"/>
  <scenario:civilian scenario:location="51195"/>
  <scenario:civilian scenario:location="51199"/>
  <scenario:civilian scenario:location="51193"/>
  <scenario:civilian scenario:location="51194"/>
  <scenario:civilian scenario:location="52175"/>
  <scenario:civilian scenario:location="24366"/>
  <scenario:civilian scenario:location="3562"/>
  <scenario:civilian scenario:location="50549"/>
  <scenario:civilian scenario:location="51709"/>
  <scenario:civilian scenario:location="49442"/>
  <scenario:civilian scenario:location="52923"/>
  <scenario:civilian scenario:location="248"/>
  <scenario:civilian scenario:location="946"/>
  <scenario:civilian scenario:location="47785"/>
  <scenario:civilian scenario:location="49803"/>
  <scenario:civilian scenario:location="51729"/>
  <scenario:civilian scenario:location="53739"/>
  <scenario:civilian scenario:location="3112"/>
  <scenario:civilian scenario:location="52685"/>
  <scenario:civilian scenario:location="52035"/>
  <scenario:civilian scenario:location="51910"/>
  <scenario:civilian scenario:location="49469"/>
  <scenario:civilian scenario:location="7270"/>
  <scenario:civilian scenario:location="48413"/>
  <scenario:civilian scenario:location="5866"/>
  <scenario:civilian scenario:location="50212"/>
  <scenario:civilian scenario:location="53280"/>
  <scenario:civilian scenario:location="3994"/>
  <scenario:civilian scenario:location="49932"/>
  <scenario:civilian scenario:location="52444"/>
  <scenario:civilian scenario:location="11855"/>
  <scenario:civilian scenario:location="52857"/>
  <scenario:civilian scenario:location="51692"/>
  <scenario:civilian scenario:location="48418"/>
  <scenario:civilian scenario:location="53558"/>
  <scenario:civilian scenario:location="52603"/>
  <scenario:civilian scenario:location="51594"/>
  <scenario:civilian scenario:location="11123"/>
  <scenario:civilian scenario:location="52508"/>
  <scenario:civilian scenario:location="49381"/>
  <scenario:civilian scenario:location="51570"/>
  <scenario:civilian scenario:location="49978"/>
  <scenario:civilian scenario:location="49574"/>
  <scenario:civilian scenario:location="2860"/>
  <scenario:civilian scenario:location="20833"/>
  <scenario:civilian scenario:location="49432"/>
  <scenario:civilian scenario:location="51169"/>
  <scenario:civilian scenario:location="52729"/>
  <scenario:civilian scenario:location="53003"/>
  <scenario:civilian scenario:location="50120"/>
  <scenario:civilian scenario:location="52792"/>
  <scenario:civilian scenario:location="52697"/>
  <scenario:civilian scenario:location="1031"/>
  <scenario:civilian scenario:location="51016"/>
  <scenario:civilian scenario:location="49551"/>
  <scenario:civilian scenario:location="49546"/>
  <scenario:civilian scenario:location="49547"/>
  <scenario:civilian scenario:location="49537"/>
  <scenario:civilian scenario:location="49533"/>
  <scenario:civilian scenario:location="49561"/>
  <scenario:civilian scenario:location="49558"/>
  <scenario:civilian scenario:location="49555"/>
  <scenario:civilian scenario:location="49555"/>
  <scenario:civilian scenario:location="49554"/>
  <scenario:civilian scenario:location="49556"/>
  <scenario:civilian scenario:location="49554"/>
  <scenario:civilian scenario:location="53536"/>
  <scenario:civilian scenario:location="49559"/>
  <scenario:civilian scenario:location="49545"/>
  <scenario:civilian scenario:location="49547"/>
  <scenario:civilian scenario:location="49534"/>
  <scenario:civilian scenario:location="49538"/>
  <scenario:civilian scenario:location="49505"/>
  <scenario:civilian scenario:location="49510"/>
  <scenario:civilian scenario:location="49507"/>
  <scenario:civilian scenario:location="49503"/>
  <scenario:civilian scenario:location="49490"/>
  <scenario:civilian scenario:location="49686"/>
  <scenario:civilian scenario:location="49746"/>
  <scenario:civilian scenario:location="49746"/>
  <scenario:civilian scenario:location="49600"/>
  <scenario:civilian scenario:location="53535"/>
  <scenario:civilian scenario:location="49544"/>
  <scenario:civilian scenario:location="49524"/>
  <scenario:civilian scenario:location="49472"/>
  <scenario:civilian scenario:location="51233"/>
  <scenario:civilian scenario:location="51258"/>
  <scenario:civilian scenario:location="51261"/>
  <scenario:civilian scenario:location="51260"/>
  <scenario:civilian scenario:location="51255"/>
  <scenario:civilian scenario:location="4138"/>
  <scenario:civilian scenario:location="51335"/>
  <scenario:civilian scenario:location="51334"/>
  <scenario:civilian scenario:location="51335"/>
  <scenario:civilian scenario:location="51402"/>
  <scenario:civilian scenario:location="49996"/>
  <scenario:civilian scenario:location="49945"/>
  <scenario:civilian scenario:location="49483"/>
  <scenario:firebrigade scenario:location="51168"/>
  <scenario:firebrigade scenario:location="51168"/>
  <scenario:firebrigade scenario:location="51168"/>
  <scenario:firebrigade scenario:location="51168"/>
  <scenario:firebrigade scenario:location="51167"/>
  <scenario:firebrigade scenario:location="51167"/>
  <scenario:firebrigade scenario:location="51167"/>
  <scenario:firebrigade scenario:location="51167"/>
  <scenario:firebrigade scenario:location="53188"/>
  <scenario:firebrigade scenario:location="53188"/>
  <scenario:firebrigade scenario:location="53188"/>
  <scenario:firebrigade scenario:location="53188"/>
  <scenario:firebrigade scenario:location="53187"/>
  <scenario:firebrigade scenario:location="53187"/>
  <scenario:firebrigade scenario:location="53187"/>
  <scenario:firebrigade scenario:location="53187"/>
  <scenario:firebrigade scenario:location="51168"/>
  <scenario:firebrigade scenario:location="51168"/>
  <scenario:firebrigade scenario:location="51168"/>
  <scenario:firebrigade scenario:location="51168"/>
  <scenario:firebrigade scenario:location="51167"/>
  <scenario:firebrigade scenario:location="51167"/>
  <scenario:firebrigade scenario:location="51167"/>
  <scenario:firebrigade scenario:location="51167"/>
  <scenario:firebrigade scenario:location="53188"/>
  <scenario:firebrigade scenario:location="53188"/>
  <scenario:firebrigade scenario:location="53188"/>
  <scenario:firebrigade scenario:location="53188"/>
  <scenario:firebrigade scenario:location="53187"/>
  <scenario:firebrigade scenario:location="53187"/>
  <scenario:firebrigade scenario:location="53187"/>
  <scenario:firebrigade scenario:location="53187"/>
  <scenario:policeforce scenario:location="47586"/>
  <scenario:policeforce scenario:location="47586"/>
  <scenario:policeforce scenario:location="47586"/>
  <scenario:policeforce scenario:location="47586"/>
  <scenario:policeforce scenario:location="47586"/>
  <scenario:policeforce scenario:location="47586"/>
  <scenario:policeforce scenario:location="47586"/>
  <scenario:policeforce scenario:location="47586"/>
  <scenario:policeforce scenario:location="3688"/>
  <scenario:policeforce scenario:location="3688"/>
  <scenario:policeforce scenario:location="3688"/>
  <scenario:policeforce scenario:location="3688"/>
  <scenario:policeforce scenario:location="3688"/>
  <scenario:policeforce scenario:location="3688"/>
  <scenario:policeforce scenario:location="3688"/>
  <scenario:policeforce scenario:location="3688"/>
  <scenario:policeforce scenario:location="51167"/>
  <scenario:policeforce scenario:location="51167"/>
  <scenario:policeforce scenario:location="51167"/>
  <scenario:policeforce scenario:location="51167"/>
  <scenario:policeforce scenario:location="51167"/>
  <scenario:policeforce scenario:location="51167"/>
  <scenario:policeforce scenario:location="51167"/>
  <scenario:policeforce scenario:location="51167"/>
  <scenario:policeforce scenario:location="51168"/>
  <scenario:policeforce scenario:location="51168"/>
  <scenario:policeforce scenario:location="51168"/>
  <scenario:policeforce scenario:location="51168"/>
  <scenario:policeforce scenario:location="51168"/>
  <scenario:policeforce scenario:location="51168"/>
  <scenario:policeforce scenario:location="51168"/>
  <scenario:policeforce scenario:location="51168"/>
  <scenario:ambulanceteam scenario:location="53188"/>
  <scenario:ambulanceteam scenario:location="53188"/>
  <scenario:ambulanceteam scenario:location="53188"/>
  <scenario:ambulanceteam scenario:location="53188"/>
  <scenario:ambulanceteam scenario:location="53188"/>
  <scenario:ambulanceteam scenario:location="53188"/>
  <scenario:ambulanceteam scenario:location="53188"/>
  <scenario:ambulanceteam scenario:location="53188"/>
  <scenario:ambulanceteam scenario:location="53187"/>
  <scenario:ambulanceteam scenario:location="53187"/>
  <scenario:ambulanceteam scenario:location="53187"/>
  <scenario:ambulanceteam scenario:location="53187"/>
  <scenario:ambulanceteam scenario:location="53187"/>
  <scenario:ambulanceteam scenario:location="53187"/>
  <scenario:ambulanceteam scenario:location="53187"/>
  <scenario:ambulanceteam scenario:location="53187"/>
  <scenario:ambulanceteam scenario:location="3139"/>
  <scenario:ambulanceteam scenario:location="3139"/>
  <scenario:ambulanceteam scenario:location="3139"/>
  <scenario:ambulanceteam scenario:location="3139"/>
  <scenario:ambulanceteam scenario:location="3139"/>
  <scenario:ambulanceteam scenario:location="3139"/>
  <scenario:ambulanceteam scenario:location="3139"/>
  <scenario:ambulanceteam scenario:location="3139"/>
  <scenario:ambulanceteam scenario:location="3148"/>
  <scenario:ambulanceteam scenario:location="3148"/>
  <scenario:ambulanceteam scenario:location="3148"/>
  <scenario:ambulanceteam scenario:location="3148"/>
  <scenario:ambulanceteam scenario:location="3148"/>
  <scenario:ambulanceteam scenario:location="3148"/>
  <scenario:ambulanceteam scenario:location="3148"/>
  <scenario:ambulanceteam scenario:location="3148"/>
</scenario:scenario>
